omar_math/__init__.py
omar_math_tools_demo-0.0.1.dist-info/METADATA
omar_math_tools_demo-0.0.1.dist-info/WHEEL
omar_math_tools_demo-0.0.1.dist-info/licenses/LICENSE
omar_math_tools_demo-0.0.1.dist-info/RECORD
