Metadata-Version: 2.4
Name: omar-math-tools-demo
Version: 0.0.1
Summary: A simple math utility package by Omar
Author-email: Omar <omar@example.com>
License-File: LICENSE
Classifier: License :: OSI Approved :: MIT License
Classifier: Operating System :: OS Independent
Classifier: Programming Language :: Python :: 3
Requires-Python: >=3.7
